maestro_mcp/__init__.py
maestro_mcp/__main__.py
maestro_mcp/cli.py
maestro_mcp/logger.py
maestro_mcp/maestro_cli.py
maestro_mcp-0.1.4.dist-info/METADATA
maestro_mcp-0.1.4.dist-info/WHEEL
maestro_mcp-0.1.4.dist-info/entry_points.txt
maestro_mcp-0.1.4.dist-info/licenses/LICENSE
maestro_mcp-0.1.4.dist-info/RECORD
